asl_pepper_2d_sim_maps
gymified_pepper_envs
pepper_2d_iarlenv
pepper_2d_simulator
