Metadata-Version: 1.0
Name: asl-pepper-2d-sim
Version: 0.0.4
Summary: Python library for Pepper 2d simulation
Home-page: UNKNOWN
Author: Daniel Dugas
Author-email: UNKNOWN
License: UNKNOWN
Platform: UNKNOWN
